scine_molassembler/__init__.py
scine_molassembler/scine_molassembler.cpython-312-x86_64-linux-gnu.so
scine_molassembler.libs/libboost_atomic-00e6ede8.so.1.78.0
scine_molassembler.libs/libboost_filesystem-e9e1d9ac.so.1.78.0
scine_molassembler.libs/libboost_system-c0fa27da.so.1.78.0
scine_molassembler.libs/libgomp-e985bcbb.so.1.0.0
scine_molassembler-3.0.1.dist-info/METADATA
scine_molassembler-3.0.1.dist-info/WHEEL
scine_molassembler-3.0.1.dist-info/top_level.txt
scine_molassembler-3.0.1.dist-info/RECORD
