Metadata-Version: 2.1
Name: scine_molassembler
Version: 3.0.1
Summary: Inorganic molecular graph interpretation, modification and conformer generation
Home-page: https://scine.ethz.ch/download/molassembler
Author: ETH Zurich, Department of Chemistry and Applied Biosciences, Reiher Group
Author-email: scine@phys.chem.ethz.ch
Classifier: Programming Language :: Python :: 3
Classifier: Programming Language :: C++
Classifier: Development Status :: 5 - Production/Stable
Classifier: Intended Audience :: Science/Research
Classifier: License :: OSI Approved :: BSD License
Classifier: Natural Language :: English
Classifier: Topic :: Scientific/Engineering :: Chemistry
Requires-Dist: scine-utilities
